wagtail_admin_interface/__init__.py
wagtail_admin_interface/context_processors.py
wagtail_admin_interface/menu.py
wagtail_admin_interface/urls.py
wagtail_admin_interface/wagtail_hooks.py
wagtail_admin_interface/templates/wagtailadmin/pages/edit.html
wagtail_admin_interface/templates/wagtailadmin/pages/index.html
wagtail_admin_interface-0.0.7.dist-info/METADATA
wagtail_admin_interface-0.0.7.dist-info/WHEEL
wagtail_admin_interface-0.0.7.dist-info/licenses/LICENSE.md
wagtail_admin_interface-0.0.7.dist-info/RECORD
